demo/__init__.py
demo/run.py
demo/pages/__init__.py
demo/pages/mac_page.py
demo/pages/win_page.py
demo/tests/__init__.py
demo/tests/test_mac.py
demo/tests/test_win.py
testpc/__init__.py
testpc/case.py
testpc/cli.py
testpc/page.py
testpc/scaffold.py
testpc/core/__init__.py
testpc/core/api/__init__.py
testpc/core/api/request.py
testpc/core/pc/__init__.py
testpc/core/pc/element.py
testpc/core/pc/mac_driver.py
testpc/core/pc/win_driver.py
testpc/running/__init__.py
testpc/running/conf.yml
testpc/running/runner.py
testpc/testdata/__init__.py
testpc/testdata/data.py
testpc/utils/__init__.py
testpc/utils/allure_util.py
testpc/utils/common.py
testpc/utils/config.py
testpc/utils/des_util.py
testpc/utils/dingtalk.py
testpc/utils/excel.py
testpc/utils/exceptions.py
testpc/utils/log.py
testpc/utils/mail.py
testpc/utils/mysql_util.py
testpc/utils/pytest_util.py
testpc/utils/swagger_util.py
testpc-0.0.4.dist-info/METADATA
testpc-0.0.4.dist-info/WHEEL
testpc-0.0.4.dist-info/entry_points.txt
testpc-0.0.4.dist-info/top_level.txt
testpc-0.0.4.dist-info/RECORD
