Metadata-Version: 2.1
Name: testpc
Version: 0.0.4
Summary: PC端自动化测试框架
Home-page: https://gitee.com/bluepang2021/kuto
Author: 杨康
Author-email: 772840356@qq.com
Platform: Mac
Platform: Win
Classifier: Programming Language :: Python :: 3.9
Requires-Python: >=3.9
Requires-Dist: requests-toolbelt (==0.10.1)
Requires-Dist: jmespath (==0.9.5)
Requires-Dist: jsonschema (==4.17.0)
Requires-Dist: pytest (==6.2.5)
Requires-Dist: pytest-rerunfailures (==10.2)
Requires-Dist: pytest-xdist (==2.5.0)
Requires-Dist: allure-pytest (==2.9.45)
Requires-Dist: click (~=8.1.3)
Requires-Dist: loguru (==0.7.0)
Requires-Dist: urllib3 (==1.26.15)
Requires-Dist: PyYAML (~=6.0)
Requires-Dist: PyAutoGUI (==0.9.54)
Requires-Dist: opencv-python (==4.6.0.66)
Requires-Dist: pyscreeze (==0.1.28)
